debug_mcp_server_launcher-0.15.8.dist-info/licenses/LICENSE
mcp_debugger_launcher/LICENSE
mcp_debugger_launcher/__init__.py
mcp_debugger_launcher/cli.py
mcp_debugger_launcher/detectors.py
mcp_debugger_launcher/launcher.py
debug_mcp_server_launcher-0.15.8.dist-info/METADATA
debug_mcp_server_launcher-0.15.8.dist-info/WHEEL
debug_mcp_server_launcher-0.15.8.dist-info/entry_points.txt
debug_mcp_server_launcher-0.15.8.dist-info/top_level.txt
debug_mcp_server_launcher-0.15.8.dist-info/RECORD
