Metadata-Version: 2.4
Name: debug-mcp-server-launcher
Version: 0.15.8
Summary: Launcher for debug-mcp-server. This package ensures debugpy is installed and provides instructions to run the main server (Node.js or Docker).
Author-email: debugmcp <debug@sycamore.llc>
License-Expression: MIT
Project-URL: Homepage, https://github.com/debugmcp/mcp-debugger
Project-URL: Repository, https://github.com/debugmcp/mcp-debugger
Keywords: mcp,dap,debugger,debugpy,ai-agent,llm
Classifier: Development Status :: 3 - Alpha
Classifier: Intended Audience :: Developers
Classifier: Programming Language :: Python :: 3
Classifier: Programming Language :: Python :: 3.8
Classifier: Programming Language :: Python :: 3.9
Classifier: Programming Language :: Python :: 3.10
Classifier: Programming Language :: Python :: 3.11
Classifier: Topic :: Software Development :: Debuggers
Classifier: Topic :: Scientific/Engineering :: Artificial Intelligence
Requires-Python: >=3.8
License-File: LICENSE
Requires-Dist: debugpy>=1.8.14
Requires-Dist: click>=8.0.0
Dynamic: license-file
